ouisparql/__init__.py
ouisparql/ouisparql.py
ouisparql/py.typed
ouisparql/queries.py
ouisparql/query_loader.py
ouisparql/types.py
ouisparql/utils.py
ouisparql/adapters/__init__.py
ouisparql/adapters/generic.py
ouisparql/adapters/pyformat.py
ouisparql/adapters/sparqlwrapper.py
ouisparql-0.1.0.dist-info/licenses/LICENSE
ouisparql-0.1.0.dist-info/METADATA
ouisparql-0.1.0.dist-info/WHEEL
ouisparql-0.1.0.dist-info/top_level.txt
ouisparql-0.1.0.dist-info/RECORD
