Metadata-Version: 2.4
Name: ouisparql
Version: 0.1.0
Summary: Simple SPARQL in Python
Author-email: Samuel Ortion <samuel@ortion.fr>
License-Expression: BSD-2-Clause
Project-URL: repository, https://gitlab.com/sortion/ouisparql
Project-URL: documentation, https://sortion.gitlab.io/ouisparql/
Project-URL: issues, https://gitlab.com/sortion/ouisparql/-/issues
Project-URL: package, https://pypi.org/project/ouisparql/
Classifier: Programming Language :: Python :: 3
Classifier: Operating System :: OS Independent
Classifier: Development Status :: 5 - Production/Stable
Classifier: Intended Audience :: Developers
Classifier: Topic :: Database
Classifier: Topic :: Software Development :: Libraries :: Python Modules
Requires-Python: >=3.9
License-File: LICENSE
Requires-Dist: sparqlwrapper
Provides-Extra: dev
Requires-Dist: pytest; extra == "dev"
Requires-Dist: pytest-asyncio; extra == "dev"
Requires-Dist: coverage; extra == "dev"
Requires-Dist: black; extra == "dev"
Requires-Dist: flake8; extra == "dev"
Requires-Dist: ruff; extra == "dev"
Requires-Dist: mypy; extra == "dev"
Requires-Dist: pyright; extra == "dev"
Requires-Dist: types-setuptools; extra == "dev"
Provides-Extra: doc
Requires-Dist: sphinx; extra == "doc"
Requires-Dist: sphinx-rtd-theme; extra == "doc"
Requires-Dist: rstcheck; extra == "doc"
Provides-Extra: dist
Requires-Dist: build; extra == "dist"
Requires-Dist: wheel; extra == "dist"
Requires-Dist: twine; extra == "dist"
Dynamic: license-file
